timeeval/__init__.py
timeeval/_version.py
timeeval/algorithm.py
timeeval/constants.py
timeeval/data_types.py
timeeval/py.typed
timeeval/remote_configuration.py
timeeval/resource_constraints.py
timeeval/timeeval.py
timeeval/_core/__init__.py
timeeval/_core/experiments.py
timeeval/_core/remote.py
timeeval/_core/times.py
timeeval/adapters/__init__.py
timeeval/adapters/base.py
timeeval/adapters/distributed.py
timeeval/adapters/docker.py
timeeval/adapters/function.py
timeeval/adapters/jar.py
timeeval/adapters/multivar.py
timeeval/algorithms/__init__.py
timeeval/algorithms/arima.py
timeeval/algorithms/autoencoder.py
timeeval/algorithms/bagel.py
timeeval/algorithms/baseline_increasing.py
timeeval/algorithms/baseline_normal.py
timeeval/algorithms/baseline_random.py
timeeval/algorithms/cblof.py
timeeval/algorithms/cof.py
timeeval/algorithms/copod.py
timeeval/algorithms/dae.py
timeeval/algorithms/damp.py
timeeval/algorithms/dbstream.py
timeeval/algorithms/deepant.py
timeeval/algorithms/deepnap.py
timeeval/algorithms/donut.py
timeeval/algorithms/dspot.py
timeeval/algorithms/dwt_mlead.py
timeeval/algorithms/eif.py
timeeval/algorithms/encdec_ad.py
timeeval/algorithms/ensemble_gi.py
timeeval/algorithms/fast_mcd.py
timeeval/algorithms/fft.py
timeeval/algorithms/generic_rf.py
timeeval/algorithms/generic_xgb.py
timeeval/algorithms/grammarviz3.py
timeeval/algorithms/grammarviz3_multi.py
timeeval/algorithms/hbos.py
timeeval/algorithms/health_esn.py
timeeval/algorithms/hif.py
timeeval/algorithms/hotsax.py
timeeval/algorithms/hybrid_knn.py
timeeval/algorithms/if_lof.py
timeeval/algorithms/iforest.py
timeeval/algorithms/img_embedding_cae.py
timeeval/algorithms/kmeans.py
timeeval/algorithms/knn.py
timeeval/algorithms/laser_dbn.py
timeeval/algorithms/left_stampi.py
timeeval/algorithms/lof.py
timeeval/algorithms/lstm_ad.py
timeeval/algorithms/lstm_vae.py
timeeval/algorithms/median_method.py
timeeval/algorithms/mscred.py
timeeval/algorithms/mstamp.py
timeeval/algorithms/mtad_gat.py
timeeval-1.5.0.dist-info/licenses/LICENSE
timeeval-1.5.0.dist-info/METADATA
timeeval-1.5.0.dist-info/WHEEL
timeeval-1.5.0.dist-info/top_level.txt
timeeval-1.5.0.dist-info/RECORD
