Metadata-Version: 2.4
Name: TimeEval
Version: 1.5.0
Summary: Evaluation Tool for Time Series Anomaly Detection Methods
Home-page: https://github.com/TimeEval/TimeEval
Author-email: Sebastian Schmidl <sebastian.schmidl@hpi.de>, Phillip Wenig <phillip.wenig@hpi.de>
License-Expression: MIT
Classifier: Programming Language :: Python
Classifier: Programming Language :: Python :: 3
Classifier: Programming Language :: Python :: 3.9
Classifier: Programming Language :: Python :: 3.10
Classifier: Programming Language :: Python :: 3.11
Classifier: Programming Language :: Python :: 3.12
Classifier: Typing :: Typed
Classifier: Topic :: Software Development
Classifier: Topic :: Scientific/Engineering
Classifier: Intended Audience :: Science/Research
Classifier: Intended Audience :: Developers
Requires-Python: <3.13,>=3.9
License-File: LICENSE
Requires-Dist: scikit-learn>=1.0.0
Requires-Dist: matplotlib>=3.5.0
Requires-Dist: numpy>=1.25.0
Requires-Dist: pandas>=1.3.0
Requires-Dist: statsmodels>=0.12.2
Requires-Dist: jinja2>=3.0.0
Requires-Dist: tqdm>=4.54.0
Requires-Dist: asyncssh>=2.5.0
Requires-Dist: psutil
Requires-Dist: dask[distributed]==2022.12.1
Requires-Dist: click>=8.0.2
Requires-Dist: docker>=4.4.0
Requires-Dist: durations>=0.3.0
Requires-Dist: prts==1.0.0.3
Requires-Dist: numpyencoder>=0.3.0
Provides-Extra: ci
Requires-Dist: pytest; extra == "ci"
Requires-Dist: pytest-cov; extra == "ci"
Requires-Dist: freezegun; extra == "ci"
Requires-Dist: mypy==1.15.0; extra == "ci"
Requires-Dist: flake8==7.2.0; extra == "ci"
Requires-Dist: black==25.1.0; extra == "ci"
Requires-Dist: isort==6.0.1; extra == "ci"
Requires-Dist: pre-commit; extra == "ci"
Requires-Dist: pythresh>=0.2.8; extra == "ci"
Requires-Dist: optuna>=3.1.0; extra == "ci"
Requires-Dist: types-requests; extra == "ci"
Requires-Dist: types-freezegun; extra == "ci"
Provides-Extra: dev
Requires-Dist: multiprocessing_logging; extra == "dev"
Requires-Dist: jupyterlab; extra == "dev"
Requires-Dist: wfdb; extra == "dev"
Requires-Dist: tables; extra == "dev"
Requires-Dist: pyyaml; extra == "dev"
Requires-Dist: pylustrator==1.1.0; extra == "dev"
Requires-Dist: plotly==5.1; extra == "dev"
Requires-Dist: bokeh>=0.13.0; extra == "dev"
Dynamic: description
Dynamic: description-content-type
Dynamic: home-page
Dynamic: license-file
